brave/__init__.py
brave/__main__.py
brave/app_container.py
brave/app_manager.py
brave/main.py
brave/setup_routes.py
brave/api/__init__.py
brave/api/config/__init__.py
brave/api/config/config.py
brave/api/config/db.py
brave/api/core/__init__.py
brave/api/core/base_event_router.py
brave/api/core/direct_dispatch.py
brave/api/core/evenet_bus.py
brave/api/core/event.py
brave/api/core/heartbeat.py
brave/api/core/pubsub.py
brave/api/core/queued_dispatch.py
brave/api/core/routers_name.py
brave/api/core/workflow_queue.py
brave/api/core/workflow_sse.py
brave/api/core/routers/__init__.py
brave/api/core/routers/analysis_executer_router.py
brave/api/core/routers/analysis_result_router.py
brave/api/core/routers/ingress_event_router.py
brave/api/core/routers/watch_file_event_router.py
brave/api/core/routers/workflow_event_router.py
brave/api/enum/__init__.py
brave/api/enum/component_script.py
brave/api/executor/__init__.py
brave/api/executor/base.py
brave/api/executor/docker_excutor.py
brave/api/executor/factory.py
brave/api/executor/k8s_executor.py
brave/api/executor/local_executor.py
brave/api/executor/models.py
brave/api/executor/slurm_executor.py
brave/api/handlers/__init__.py
brave/api/handlers/analysis_executer.py
brave/api/handlers/analysis_result.py
brave/api/handlers/workflow_events.py
brave/api/ingress/__init__.py
brave/api/ingress/factory.py
brave/api/ingress/http_ingress.py
brave/api/ingress/manager.py
brave/api/ingress/uds_socket.py
brave/api/ingress/uds_stream.py
brave/api/ingress/interfaces/__init__.py
brave/api/ingress/interfaces/base_ingress.py
brave/api/listener/__init__.py
brave/api/listener/file_tarce.py
brave/api/models/__init__.py
brave/api/models/core.py
brave/api/models/orm.py
brave/api/routes/__init__.py
brave/api/routes/analysis.py
brave/api/routes/bio_database.py
brave/api/routes/component_store.py
brave/api/routes/container.py
brave/api/routes/file_operation.py
brave/api/routes/file_parse_plot.py
brave/api/routes/index.py
brave/api/routes/kegg.py
pybrave-0.2.4.dist-info/licenses/LICENSE
pybrave-0.2.4.dist-info/METADATA
pybrave-0.2.4.dist-info/WHEEL
pybrave-0.2.4.dist-info/entry_points.txt
pybrave-0.2.4.dist-info/top_level.txt
pybrave-0.2.4.dist-info/RECORD
