Metadata-Version: 2.4
Name: pybrave
Version: 0.2.4
Summary: Bioinformatics Reactive Analysis and Visualization Engine
Author: WangYang
Project-URL: Source, https://github.com/pybrave/brave
Project-URL: Tracker, https://github.com/pybrave/brave
Project-URL: Documentation, https://github.com/pybrave/brave
Requires-Python: >=3.7
License-File: LICENSE
Requires-Dist: fastapi
Requires-Dist: sqlalchemy
Requires-Dist: pandas
Requires-Dist: uvicorn[standard]
Requires-Dist: typer
Requires-Dist: pymysql
Requires-Dist: click==8.1.8
Requires-Dist: dependency-injector<5.0,>=4.0
Requires-Dist: docker
Requires-Dist: kubernetes
Requires-Dist: psutil
Requires-Dist: httpx
Requires-Dist: nbformat
Requires-Dist: PyMuPDF
Requires-Dist: py2neo
Requires-Dist: python-multipart
Requires-Dist: aiofiles
Requires-Dist: shortuuid
Requires-Dist: aiohttp
Requires-Dist: Bio
Requires-Dist: nbconvert
Requires-Dist: lxml
Requires-Dist: cryptography
Dynamic: author
Dynamic: description
Dynamic: description-content-type
Dynamic: license-file
Dynamic: project-url
Dynamic: requires-dist
Dynamic: requires-python
Dynamic: summary
